detector_worker/__init__.py
detector_worker/common.py
detector_worker/gazetteer.py
detector_worker/sentencizer.py
detector_worker/worker.py
detector_worker-0.5.1.2.dist-info/METADATA
detector_worker-0.5.1.2.dist-info/WHEEL
detector_worker-0.5.1.2.dist-info/top_level.txt
detector_worker-0.5.1.2.dist-info/RECORD
